PriscillaAndAquila-0.0.1a6.dist-info/METADATA
PriscillaAndAquila-0.0.1a6.dist-info/RECORD
PriscillaAndAquila-0.0.1a6.dist-info/WHEEL
PriscillaAndAquila-0.0.1a6.dist-info/entry_points.txt
PriscillaAndAquila-0.0.1a6.dist-info/top_level.txt
priscillaandaquila/__init__.py
priscillaandaquila/args.py
priscillaandaquila/main.py
