Metadata-Version: 2.1
Name: PriscillaAndAquila
Version: 0.0.1a6
Summary: A command line tool that performs a lookup of Bible verse references that can be fed in through various input means.
Home-page: https://github.com/alextricity25/PriscillaAndAquila
Author: Miguel Alex Cantu
Author-email: miguel.can2@gmail.com
License: GNU General Public License v3 or later (GPLv3+)
Download-URL: https://github.com/alextricity25/PriscillaAndAquila/archive/0.0.1a6.tar.gz
Keywords: Study Bible,Memorize Bible,Holy Scriptures
Platform: UNKNOWN
Requires-Dist: diyr
